setup.py
qzig/__init__.py
qzig/application.py
qzig/device.py
qzig/gateway.py
qzig/json_rpc.py
qzig/main.py
qzig/model.py
qzig/network.py
qzig/state.py
qzig/status.py
qzig/util.py
qzig/value.py
qzig/zigbee.py
qzig.egg-info/PKG-INFO
qzig.egg-info/SOURCES.txt
qzig.egg-info/dependency_links.txt
qzig.egg-info/entry_points.txt
qzig.egg-info/requires.txt
qzig.egg-info/top_level.txt
qzig/values/__init__.py
qzig/values/diagnostics.py
qzig/values/humidity.py
qzig/values/identify.py
qzig/values/kaercher.py
qzig/values/onoff.py
qzig/values/ota.py
qzig/values/power.py
qzig/values/temperature.py
tests/__init__.py
tests/conftest.py
tests/test_application.py
tests/test_main.py
tests/test_rpc.py
tests/test_zigbee.py
tests/util.py