Metadata-Version: 1.1
Name: qzig
Version: 0.0.4
Summary: A ZigBee convertor for Seluxit IoT platform
Home-page: http://iot.seluxit.com
Author: Andreas Bomholtz
Author-email: andreas@seluxit.com
License: GPL-3.0
Download-URL: https://github.com/Seluxit/qzig
Keywords: zigbee iot seluxit converter
Platform: Linux
Classifier: Development Status :: 2 - Pre-Alpha
Classifier: Environment :: Console
Classifier: Environment :: No Input/Output (Daemon)
Classifier: Framework :: AsyncIO
Classifier: Framework :: Flake8
Classifier: Intended Audience :: Developers
Classifier: License :: OSI Approved :: GNU General Public License v3 (GPLv3)
Classifier: Operating System :: POSIX :: Linux
Classifier: Operating System :: Unix
Classifier: Programming Language :: Python :: 3.4
Classifier: Programming Language :: Python :: 3.5
Classifier: Topic :: Software Development :: Embedded Systems
Classifier: Topic :: Software Development :: Interpreters
Classifier: Topic :: Software Development :: Libraries :: Python Modules
Requires: bellows
